Metadata-Version: 2.1
Name: logmag
Version: 1.1
Summary: Logging
Home-page: UNKNOWN
Author-email: zhassulanissayev@gmail.com
License: UNKNOWN
Platform: UNKNOWN
